vsphere_guest_run/__init__.py
vsphere_guest_run/vgr.py
vsphere_guest_run/vsphere.py
vsphere_guest_run-0.0.7.dist-info/METADATA
vsphere_guest_run-0.0.7.dist-info/RECORD
vsphere_guest_run-0.0.7.dist-info/WHEEL
vsphere_guest_run-0.0.7.dist-info/entry_points.txt
vsphere_guest_run-0.0.7.dist-info/pbr.json
vsphere_guest_run-0.0.7.dist-info/top_level.txt
