Metadata-Version: 2.1
Name: vsphere-guest-run
Version: 0.0.7
Summary: vSphere Guest Run
Home-page: https://github.com/vmware/vsphere-guest-run
Author: Paco Gomez
Author-email: pgomez@vmware.com
License: UNKNOWN
Platform: UNKNOWN
Classifier: Environment :: Console
Classifier: Intended Audience :: System Administrators
Classifier: Intended Audience :: Developers
Classifier: Operating System :: POSIX :: Linux
Classifier: Operating System :: MacOS :: MacOS X
Classifier: Operating System :: Microsoft :: Windows
Classifier: Programming Language :: Python
Classifier: Programming Language :: Python :: 3
Requires-Dist: click (>=6.7)
Requires-Dist: pygments (>=2.2.0)
Requires-Dist: pyvmomi (>=6.5.0.2017.5.post1)
Requires-Dist: tabulate (>=0.8.2)
